linotype/__init__.py
linotype/ansi.py
linotype/ext.py
linotype/items.py
linotype-0.2.1.dist-info/DESCRIPTION.rst
linotype-0.2.1.dist-info/METADATA
linotype-0.2.1.dist-info/RECORD
linotype-0.2.1.dist-info/WHEEL
linotype-0.2.1.dist-info/metadata.json
linotype-0.2.1.dist-info/top_level.txt
