Metadata-Version: 2.0
Name: linotype
Version: 0.2.1
Summary: Automatically format help messages.
Home-page: https://github.com/lostatc/linotype
Author: Garrett Powell
Author-email: garrett@gpowell.net
License: GPLv3
Platform: UNKNOWN
Classifier: Intended Audience :: Developers
Classifier: License :: OSI Approved :: GNU General Public License v3 or later (GPLv3+)
Classifier: Operating System :: MacOS
Classifier: Operating System :: Microsoft :: Windows
Classifier: Operating System :: POSIX
Classifier: Programming Language :: Python :: 3
Classifier: Topic :: Software Development :: Documentation
Requires-Python: >=3.5
Requires-Dist: sphinx
Provides-Extra: Windows support
Requires-Dist: colorama; extra == 'Windows support'
